LICENSE.rst
MANIFEST.in
README.rst
setup.cfg
setup.py
dtool_cli/__init__.py
dtool_cli/cli.py
dtool_cli.egg-info/PKG-INFO
dtool_cli.egg-info/SOURCES.txt
dtool_cli.egg-info/dependency_links.txt
dtool_cli.egg-info/entry_points.txt
dtool_cli.egg-info/requires.txt
dtool_cli.egg-info/top_level.txt