Metadata-Version: 1.1
Name: dtool-cli
Version: 0.7.1
Summary: Data management command line tool: dtool.
Home-page: https://github.com/jic-dtool/dtool-cli
Author: Tjelvar Olsson
Author-email: tjelvar.olsson@gmail.com
License: MIT
Download-URL: https://github.com/jic-dtool/dtool-cli/tarball/0.7.1
Platform: UNKNOWN
